boxus
