Metadata-Version: 1.1
Name: boxus
Version: 0.1.1
Summary: High-level framework for easy control of multiple devices connected to the Raspberry Pi and Arduino via GPIO
Home-page: https://github.com/boxus-plants/boxus
Author: Alexey Kondratov
Author-email: kondratov.aleksey@gmail.com
License: GNU General Public License v3.0
Download-URL: https://pypi.python.org/pypi/boxus
Platform: UNKNOWN
